{
  "_comment" : "Created with OWL2VOWL (version 0.3.5), http://vowl.visualdataweb.org",
  "header" : {
    "languages" : [ "en", "undefined" ],
    "baseIris" : [ "http://www.w3.org/1999/02/22-rdf-syntax-ns", "https://w3id.org/koro", "http://www.w3.org/2000/01/rdf-schema", "http://purl.org/dc/terms", "http://www.w3.org/2001/XMLSchema", "http://xmlns.com/foaf/0.1", "http://www.bbc.co.uk/ontologies/coreconcepts" ],
    "title" : {
      "en" : "Kitchen Object Reasoning Ontology"
    },
    "iri" : "https://w3id.org/koro#",
    "version" : "1.0.0",
    "author" : [ "_:genid2147483648" ],
    "description" : {
      "en" : "An ontology to model a kitchen environment and properties related to cleaning tasks for a robot agent."
    },
    "other" : {
      "license" : [ {
        "identifier" : "license",
        "language" : "undefined",
        "value" : "https://creativecommons.org/licenses/by/4.0/",
        "type" : "iri"
      } ],
      "creator" : [ {
        "identifier" : "creator",
        "language" : "undefined",
        "value" : "_:genid2147483648",
        "type" : "label"
      } ],
      "created" : [ {
        "identifier" : "created",
        "language" : "undefined",
        "value" : "2025-05-28",
        "type" : "label"
      } ],
      "preferredNamespacePrefix" : [ {
        "identifier" : "preferredNamespacePrefix",
        "language" : "undefined",
        "value" : "koro",
        "type" : "label"
      } ],
      "versionInfo" : [ {
        "identifier" : "versionInfo",
        "language" : "undefined",
        "value" : "1.0.0",
        "type" : "label"
      } ],
      "preferredNamespaceUri" : [ {
        "identifier" : "preferredNamespaceUri",
        "language" : "undefined",
        "value" : "https://w3id.org/koro#",
        "type" : "label"
      } ],
      "title" : [ {
        "identifier" : "title",
        "language" : "en",
        "value" : "Kitchen Object Reasoning Ontology",
        "type" : "label"
      } ]
    }
  },
  "namespace" : [ ],
  "class" : [ {
    "id" : "9",
    "type" : "owl:Class"
  }, {
    "id" : "10",
    "type" : "rdfs:Datatype"
  }, {
    "id" : "1",
    "type" : "owl:Thing"
  }, {
    "id" : "2",
    "type" : "rdfs:Literal"
  }, {
    "id" : "15",
    "type" : "rdfs:Literal"
  }, {
    "id" : "16",
    "type" : "rdfs:Literal"
  }, {
    "id" : "17",
    "type" : "owl:Class"
  }, {
    "id" : "18",
    "type" : "owl:Class"
  }, {
    "id" : "19",
    "type" : "owl:Class"
  }, {
    "id" : "8",
    "type" : "rdfs:Datatype"
  }, {
    "id" : "12",
    "type" : "rdfs:Datatype"
  }, {
    "id" : "21",
    "type" : "owl:Class"
  }, {
    "id" : "5",
    "type" : "owl:Class"
  }, {
    "id" : "22",
    "type" : "owl:Class"
  }, {
    "id" : "7",
    "type" : "owl:Class"
  }, {
    "id" : "25",
    "type" : "owl:Class"
  }, {
    "id" : "26",
    "type" : "owl:Class"
  }, {
    "id" : "28",
    "type" : "owl:Class"
  }, {
    "id" : "4",
    "type" : "owl:Class"
  }, {
    "id" : "31",
    "type" : "owl:Class"
  } ],
  "classAttribute" : [ {
    "iri" : "https://w3id.org/koro#Furniture",
    "baseIri" : "https://w3id.org/koro",
    "instances" : 0,
    "label" : {
      "IRI-based" : "Furniture",
      "en" : "Furniture"
    },
    "comment" : {
      "en" : "A piece of furniture in the kitchen."
    },
    "id" : "9"
  }, {
    "iri" : "http://www.w3.org/2001/XMLSchema#float",
    "baseIri" : "http://www.w3.org/2001/XMLSchema",
    "id" : "10",
    "label" : {
      "IRI-based" : "float"
    }
  }, {
    "iri" : "http://www.w3.org/2002/07/owl#Thing",
    "baseIri" : "http://owl2vowl.de",
    "id" : "1",
    "label" : {
      "undefined" : "Thing"
    }
  }, {
    "iri" : "http://www.w3.org/2000/01/rdf-schema#Literal",
    "id" : "2",
    "label" : {
      "IRI-based" : "Literal",
      "undefined" : "Literal"
    }
  }, {
    "iri" : "http://www.w3.org/2000/01/rdf-schema#Literal",
    "id" : "15",
    "label" : {
      "IRI-based" : "Literal",
      "undefined" : "Literal"
    }
  }, {
    "iri" : "http://www.w3.org/2000/01/rdf-schema#Literal",
    "id" : "16",
    "label" : {
      "IRI-based" : "Literal",
      "undefined" : "Literal"
    }
  }, {
    "iri" : "http://www.bbc.co.uk/ontologies/coreconcepts/preferredLabel",
    "baseIri" : "http://www.bbc.co.uk/ontologies/coreconcepts",
    "instances" : 0,
    "label" : {
      "IRI-based" : "preferredLabel"
    },
    "attributes" : [ "external" ],
    "id" : "17"
  }, {
    "iri" : "https://w3id.org/koro#Furnishing",
    "baseIri" : "https://w3id.org/koro",
    "instances" : 0,
    "label" : {
      "IRI-based" : "Furnishing",
      "en" : "Table Chair"
    },
    "comment" : {
      "en" : "A furniture in the kitchen, such as tables and chairs."
    },
    "id" : "18"
  }, {
    "iri" : "https://w3id.org/koro#Storage",
    "baseIri" : "https://w3id.org/koro",
    "instances" : 0,
    "label" : {
      "IRI-based" : "Storage",
      "en" : "Storage"
    },
    "comment" : {
      "en" : "A storage component in the kitchen."
    },
    "id" : "19"
  }, {
    "iri" : "http://www.w3.org/2001/XMLSchema#float",
    "baseIri" : "http://www.w3.org/2001/XMLSchema",
    "id" : "8",
    "label" : {
      "IRI-based" : "float"
    }
  }, {
    "iri" : "http://www.w3.org/2001/XMLSchema#float",
    "baseIri" : "http://www.w3.org/2001/XMLSchema",
    "id" : "12",
    "label" : {
      "IRI-based" : "float"
    }
  }, {
    "iri" : "https://w3id.org/koro#Object",
    "baseIri" : "https://w3id.org/koro",
    "instances" : 0,
    "label" : {
      "IRI-based" : "Object",
      "en" : "Object"
    },
    "comment" : {
      "en" : "An object in the kitchen that can be manipulated by the robot."
    },
    "id" : "21"
  }, {
    "iri" : "https://w3id.org/koro#Location",
    "baseIri" : "https://w3id.org/koro",
    "instances" : 0,
    "label" : {
      "IRI-based" : "Location",
      "en" : "Location"
    },
    "comment" : {
      "en" : "The location of a component."
    },
    "id" : "5"
  }, {
    "iri" : "http://www.w3.org/2000/01/rdf-schema#label",
    "baseIri" : "http://www.w3.org/2000/01/rdf-schema",
    "instances" : 0,
    "label" : {
      "IRI-based" : "label"
    },
    "attributes" : [ "external" ],
    "id" : "22"
  }, {
    "iri" : "https://w3id.org/koro#Translation",
    "baseIri" : "https://w3id.org/koro",
    "instances" : 0,
    "label" : {
      "IRI-based" : "Translation",
      "en" : "Translation"
    },
    "comment" : {
      "en" : "The three coordinates location of a component."
    },
    "id" : "7"
  }, {
    "iri" : "https://w3id.org/koro#KitchenEnvironment",
    "baseIri" : "https://w3id.org/koro",
    "instances" : 0,
    "label" : {
      "IRI-based" : "KitchenEnvironment",
      "en" : "Kitchen Environment"
    },
    "comment" : {
      "en" : "A kitchen environment made of kitchen components."
    },
    "id" : "25"
  }, {
    "iri" : "http://purl.org/dc/terms/identifier",
    "baseIri" : "http://purl.org/dc/terms",
    "instances" : 0,
    "label" : {
      "IRI-based" : "identifier"
    },
    "attributes" : [ "external" ],
    "id" : "26"
  }, {
    "iri" : "https://w3id.org/koro#Appliance",
    "baseIri" : "https://w3id.org/koro",
    "instances" : 0,
    "label" : {
      "IRI-based" : "Appliance",
      "en" : "Appliance"
    },
    "comment" : {
      "en" : "An appliance in the kitchen."
    },
    "id" : "28"
  }, {
    "iri" : "https://w3id.org/koro#Component",
    "baseIri" : "https://w3id.org/koro",
    "instances" : 0,
    "label" : {
      "IRI-based" : "Component",
      "en" : "Component"
    },
    "comment" : {
      "en" : "A component in the kitchen environment."
    },
    "id" : "4"
  }, {
    "iri" : "http://xmlns.com/foaf/0.1/Person",
    "baseIri" : "http://xmlns.com/foaf/0.1",
    "instances" : 0,
    "label" : {
      "IRI-based" : "Person"
    },
    "attributes" : [ "external" ],
    "id" : "31"
  } ],
  "property" : [ {
    "id" : "0",
    "type" : "owl:datatypeProperty"
  }, {
    "id" : "3",
    "type" : "owl:objectProperty"
  }, {
    "id" : "6",
    "type" : "owl:datatypeProperty"
  }, {
    "id" : "11",
    "type" : "owl:datatypeProperty"
  }, {
    "id" : "13",
    "type" : "owl:objectProperty"
  }, {
    "id" : "14",
    "type" : "owl:datatypeProperty"
  }, {
    "id" : "20",
    "type" : "owl:objectProperty"
  }, {
    "id" : "23",
    "type" : "owl:datatypeProperty"
  }, {
    "id" : "24",
    "type" : "owl:datatypeProperty"
  }, {
    "id" : "27",
    "type" : "owl:objectProperty"
  }, {
    "id" : "29",
    "type" : "owl:objectProperty"
  }, {
    "id" : "30",
    "type" : "owl:objectProperty"
  } ],
  "propertyAttribute" : [ {
    "iri" : "https://w3id.org/koro#hasIdentifier",
    "baseIri" : "https://w3id.org/koro",
    "range" : "2",
    "label" : {
      "IRI-based" : "hasIdentifier",
      "undefined" : "has identifier"
    },
    "domain" : "1",
    "comment" : {
      "undefined" : "Indicates the identifier of the object."
    },
    "attributes" : [ "datatype" ],
    "id" : "0"
  }, {
    "iri" : "https://w3id.org/koro#hasCurrentLocation",
    "baseIri" : "https://w3id.org/koro",
    "range" : "5",
    "label" : {
      "IRI-based" : "hasCurrentLocation",
      "undefined" : "has current location"
    },
    "domain" : "4",
    "comment" : {
      "undefined" : "Indicates the current location of the Component as a :Location."
    },
    "attributes" : [ "object" ],
    "id" : "3"
  }, {
    "iri" : "https://w3id.org/koro#hasTranslationX",
    "baseIri" : "https://w3id.org/koro",
    "range" : "8",
    "label" : {
      "IRI-based" : "hasTranslationX",
      "undefined" : "has translation X"
    },
    "domain" : "7",
    "comment" : {
      "undefined" : "Indicates the X coordinate of the object as a :TranslationX."
    },
    "attributes" : [ "datatype" ],
    "id" : "6"
  }, {
    "iri" : "https://w3id.org/koro#hasTranslationY",
    "baseIri" : "https://w3id.org/koro",
    "range" : "12",
    "label" : {
      "IRI-based" : "hasTranslationY",
      "undefined" : "has translation Y"
    },
    "domain" : "7",
    "comment" : {
      "undefined" : "Indicates the Y coordinate of the object as a :TranslationY."
    },
    "attributes" : [ "datatype" ],
    "id" : "11"
  }, {
    "iri" : "https://w3id.org/koro#hasLocation",
    "baseIri" : "https://w3id.org/koro",
    "range" : "5",
    "label" : {
      "IRI-based" : "hasLocation",
      "undefined" : "has location"
    },
    "domain" : "4",
    "comment" : {
      "undefined" : "Indicates the location of the component."
    },
    "attributes" : [ "object" ],
    "id" : "13"
  }, {
    "iri" : "https://w3id.org/koro#hasTranslationZ",
    "baseIri" : "https://w3id.org/koro",
    "range" : "10",
    "label" : {
      "IRI-based" : "hasTranslationZ",
      "undefined" : "has translation Z"
    },
    "domain" : "7",
    "comment" : {
      "undefined" : "Indicates the Z coordinate of the object as a :TranslationZ."
    },
    "attributes" : [ "datatype" ],
    "id" : "14"
  }, {
    "iri" : "https://w3id.org/koro#hasTranslation",
    "baseIri" : "https://w3id.org/koro",
    "range" : "7",
    "label" : {
      "IRI-based" : "hasTranslation",
      "undefined" : "has translation"
    },
    "domain" : "5",
    "comment" : {
      "undefined" : "Describes the location of the object as a :Translation."
    },
    "attributes" : [ "object" ],
    "id" : "20"
  }, {
    "iri" : "https://w3id.org/koro#hasPreferredLabel",
    "baseIri" : "https://w3id.org/koro",
    "range" : "15",
    "label" : {
      "IRI-based" : "hasPreferredLabel",
      "undefined" : "has preferred label"
    },
    "domain" : "1",
    "comment" : {
      "undefined" : "Indicates the preferred label of the object."
    },
    "attributes" : [ "datatype" ],
    "id" : "23"
  }, {
    "iri" : "https://w3id.org/koro#hasLabel",
    "baseIri" : "https://w3id.org/koro",
    "range" : "16",
    "label" : {
      "IRI-based" : "hasLabel",
      "undefined" : "has label"
    },
    "domain" : "1",
    "comment" : {
      "undefined" : "Indicates a label of the object."
    },
    "attributes" : [ "datatype" ],
    "id" : "24"
  }, {
    "iri" : "https://w3id.org/koro#hasLocationComponent",
    "baseIri" : "https://w3id.org/koro",
    "range" : "4",
    "label" : {
      "IRI-based" : "hasLocationComponent",
      "undefined" : "has location component"
    },
    "domain" : "5",
    "comment" : {
      "undefined" : "Describes the location of the object as a :Component."
    },
    "attributes" : [ "object" ],
    "id" : "27"
  }, {
    "iri" : "https://w3id.org/koro#hasComponent",
    "baseIri" : "https://w3id.org/koro",
    "range" : "4",
    "label" : {
      "IRI-based" : "hasComponent",
      "en" : "has component"
    },
    "domain" : "25",
    "comment" : {
      "en" : "Relates a kitchen environment to its components."
    },
    "attributes" : [ "object" ],
    "id" : "29"
  }, {
    "iri" : "https://w3id.org/koro#hasTargetLocation",
    "baseIri" : "https://w3id.org/koro",
    "range" : "5",
    "label" : {
      "IRI-based" : "hasTargetLocation",
      "undefined" : "has target location"
    },
    "domain" : "4",
    "comment" : {
      "undefined" : "Indicates the target location of the object as a :Location."
    },
    "attributes" : [ "object" ],
    "id" : "30"
  } ]
}